sphinxcontrib_httpdomain-1.6.1-py3.6-nspkg.pth
sphinxcontrib/httpdomain.py
sphinxcontrib/autohttp/__init__.py
sphinxcontrib/autohttp/bottle.py
sphinxcontrib/autohttp/common.py
sphinxcontrib/autohttp/flask.py
sphinxcontrib/autohttp/flask_base.py
sphinxcontrib/autohttp/flaskqref.py
sphinxcontrib/autohttp/tornado.py
sphinxcontrib_httpdomain-1.6.1.dist-info/DESCRIPTION.rst
sphinxcontrib_httpdomain-1.6.1.dist-info/METADATA
sphinxcontrib_httpdomain-1.6.1.dist-info/RECORD
sphinxcontrib_httpdomain-1.6.1.dist-info/WHEEL
sphinxcontrib_httpdomain-1.6.1.dist-info/metadata.json
sphinxcontrib_httpdomain-1.6.1.dist-info/namespace_packages.txt
sphinxcontrib_httpdomain-1.6.1.dist-info/top_level.txt
