Metadata-Version: 2.0
Name: sphinxcontrib-httpdomain
Version: 1.6.1
Summary: Sphinx domain for documenting HTTP APIs
Home-page: https://github.com/sphinx-contrib/httpdomain
Author: Hong Minhee
Author-email: hong.minhee@gmail.com
License: BSD
Download-URL: https://pypi.org/project/sphinxcontrib-httpdomain/
Platform: any
Classifier: Development Status :: 5 - Production/Stable
Classifier: Environment :: Console
Classifier: Environment :: Web Environment
Classifier: Intended Audience :: Developers
Classifier: License :: OSI Approved :: BSD License
Classifier: Operating System :: OS Independent
Classifier: Programming Language :: Python
Classifier: Programming Language :: Python :: 2.7
Classifier: Programming Language :: Python :: 3.5
Classifier: Programming Language :: Python :: 3.6
Classifier: Topic :: Documentation
Classifier: Topic :: Utilities
Requires-Dist: Sphinx (>=1.5)
Requires-Dist: six
